pykeurig/__init__.py
pykeurig/const.py
pykeurig/keurigapi.py
pykeurig-1.4.3.dist-info/METADATA
pykeurig-1.4.3.dist-info/WHEEL
pykeurig-1.4.3.dist-info/top_level.txt
pykeurig-1.4.3.dist-info/RECORD
