Metadata-Version: 2.1
Name: pykeurig
Version: 1.4.3
Summary: Provides an interface to the Keurig API.
Home-page: https://github.com/dcmeglio/pykeurig
Author: Dominick Meglio
Author-email: dmeglio@gmail.com
License: MIT
Classifier: Programming Language :: Python :: 3
Classifier: License :: OSI Approved :: MIT License
Classifier: Operating System :: OS Independent
Requires-Python: >=3.6
Requires-Dist: httpx
Requires-Dist: signalrcoreplus
Requires-Dist: tzlocal
